{
    "name": "Teacher",
    "fields": [
        {
            "fieldName": "hourlyRate",
            "fieldType": "Double",
            "fieldValidateRules": [
                "required"
            ]
        }
    ],
    "relationships": [
        {
            "relationshipType": "one-to-one",
            "otherEntityName": "employee",
            "otherEntityRelationshipName": "teacher",
            "relationshipName": "employee",
            "otherEntityField": "id",
            "ownerSide": true
        },
        {
            "relationshipType": "many-to-many",
            "otherEntityName": "subject",
            "otherEntityRelationshipName": "teacher",
            "relationshipName": "subject",
            "otherEntityField": "id",
            "ownerSide": true
        }
    ],
    "changelogDate": "20190320223326",
    "entityTableName": "teacher",
    "dto": "mapstruct",
    "pagination": "pagination",
    "service": "serviceImpl",
    "jpaMetamodelFiltering": false,
    "fluentMethods": true,
    "clientRootFolder": "",
    "applications": "*"
}